hashflow/__init__.py
hashflow/client.py
hashflow/constants.py
hashflow/deployed.json
hashflow/erc20.py
hashflow/executor.py
hashflow/factory.py
hashflow/functions.py
hashflow/governance.py
hashflow/main.py
hashflow/pool.py
hashflow/router.py
hashflow/tracker.py
hashflow/util.py
hashflow/abi/IERC20.json
hashflow/abi/IHashflowERC20.json
hashflow/abi/IHashflowFactory.json
hashflow/abi/IHashflowGovernance.json
hashflow/abi/IHashflowLayerZeroUA.json
hashflow/abi/IHashflowPool.json
hashflow/abi/IHashflowPrivPool.json
hashflow/abi/IHashflowPrivatePool.json
hashflow/abi/IHashflowPublicPool.json
hashflow/abi/IHashflowRouter.json
hashflow/abi/IHashflowSpotPubPool.json
hashflow/abi/IHashflowTracker.json
hashflow/abi/IHashflowXChainUA.json
hashflow/abi/ILayerZeroEndpoint.json
hashflow/abi/ILayerZeroNonceContract.json
hashflow/abi/IWeth.json
hashflow/abi/testToken1.json
tests/__init__.py
tests/demo.py
tests/test_factory.py
tests/test_pools.py
tests/test_router.py
hashflow_sdk-0.1.0.dist-info/METADATA
hashflow_sdk-0.1.0.dist-info/WHEEL
hashflow_sdk-0.1.0.dist-info/top_level.txt
hashflow_sdk-0.1.0.dist-info/RECORD
